discord/__init__.py
discord/__main__.py
discord/_typed_dict.py
discord/_version.py
discord/abc.py
discord/activity.py
discord/appinfo.py
discord/application_role_connection.py
discord/asset.py
discord/audit_logs.py
discord/automod.py
discord/backoff.py
discord/bot.py
discord/channel.py
discord/client.py
discord/cog.py
discord/colour.py
discord/components.py
discord/context_managers.py
discord/embeds.py
discord/emoji.py
discord/enums.py
discord/errors.py
discord/file.py
discord/flags.py
discord/gateway.py
discord/guild.py
discord/http.py
discord/integrations.py
discord/interactions.py
discord/invite.py
discord/iterators.py
discord/member.py
discord/mentions.py
discord/message.py
discord/mixins.py
discord/monetization.py
discord/object.py
discord/oggparse.py
discord/onboarding.py
discord/opus.py
discord/partial_emoji.py
discord/permissions.py
discord/player.py
discord/poll.py
discord/py.typed
discord/raw_models.py
discord/reaction.py
discord/role.py
discord/scheduled_events.py
discord/shard.py
discord/stage_instance.py
discord/state.py
discord/sticker.py
discord/team.py
discord/template.py
discord/threads.py
discord/user.py
discord/utils.py
discord/voice_client.py
discord/welcome_screen.py
discord/widget.py
discord/bin/libopus-0.x64.dll
discord/bin/libopus-0.x86.dll
discord/commands/__init__.py
discord/commands/context.py
discord/commands/core.py
discord/commands/options.py
discord/commands/permissions.py
discord/ext/bridge/__init__.py
discord/ext/bridge/bot.py
discord/ext/bridge/context.py
discord/ext/bridge/core.py
discord/ext/commands/__init__.py
discord/ext/commands/_types.py
discord/ext/commands/bot.py
discord/ext/commands/cog.py
discord/ext/commands/context.py
discord/ext/commands/converter.py
discord/ext/commands/cooldowns.py
discord/ext/commands/core.py
discord/ext/commands/errors.py
discord/ext/commands/flags.py
discord/ext/commands/help.py
discord/ext/commands/view.py
discord/ext/pages/__init__.py
discord/ext/pages/pagination.py
py_cord_dev-2.8.0.dist-info/LICENSE
py_cord_dev-2.8.0.dist-info/METADATA
py_cord_dev-2.8.0.dist-info/WHEEL
py_cord_dev-2.8.0.dist-info/top_level.txt
py_cord_dev-2.8.0.dist-info/RECORD
