Metadata-Version: 2.1
Name: py-cord-dev
Version: 2.8.0
Summary: A Python wrapper for the Discord API
Author: Pycord Development
License: MIT
Project-URL: Homepage, https://pycord.dev
Project-URL: Changelog, https://docs.pycord.dev/en/master/changelog.html
Project-URL: Source, https://github.com/Pycord-Development/pycord
Project-URL: Documentation, https://docs.pycord.dev
Project-URL: Tracker, https://github.com/Pycord-Development/pycord/issues
Project-URL: Funding, https://patreon.com/pycord
Classifier: Development Status :: 1 - Planning
Classifier: License :: OSI Approved :: MIT License
Classifier: Intended Audience :: Developers
Classifier: Natural Language :: English
Classifier: Operating System :: OS Independent
Classifier: Programming Language :: Python :: 3.9
Classifier: Programming Language :: Python :: 3.10
Classifier: Programming Language :: Python :: 3.11
Classifier: Programming Language :: Python :: 3.12
Classifier: Topic :: Internet
Classifier: Topic :: Software Development :: Libraries
Classifier: Topic :: Software Development :: Libraries :: Python Modules
Classifier: Topic :: Utilities
Classifier: Typing :: Typed
Requires-Python: >=3.9
License-File: LICENSE
Requires-Dist: aiohttp <4.0,>=3.6.0
Requires-Dist: typing-extensions <5,>=4 ; python_version < "3.11"
Provides-Extra: docs
Requires-Dist: sphinx ==8.0.2 ; extra == 'docs'
Requires-Dist: sphinxcontrib-trio ==1.1.2 ; extra == 'docs'
Requires-Dist: sphinxcontrib-websupport ==2.0.0 ; extra == 'docs'
Requires-Dist: myst-parser[linkify] ==4.0.0 ; extra == 'docs'
Requires-Dist: sphinxext-opengraph ==0.9.1 ; extra == 'docs'
Requires-Dist: sphinx-copybutton ==0.5.2 ; extra == 'docs'
Requires-Dist: furo ==2024.8.6 ; extra == 'docs'
Requires-Dist: sphinx-autodoc-typehints ==2.2.3 ; extra == 'docs'
Requires-Dist: sphinx-intl ==2.2.0 ; extra == 'docs'
Requires-Dist: typing-extensions ==4.12.2 ; extra == 'docs'
Requires-Dist: levenshtein ==0.25.1 ; extra == 'docs'
Provides-Extra: speed
Requires-Dist: msgspec ~=0.18.6 ; extra == 'speed'
Requires-Dist: aiohttp[speedups] ; extra == 'speed'
Provides-Extra: voice
Requires-Dist: PyNaCl <1.6,>=1.3.0 ; extra == 'voice'
